beetsplug/notify.py
beets_notify-0.2.1.dist-info/METADATA
beets_notify-0.2.1.dist-info/WHEEL
beets_notify-0.2.1.dist-info/licenses/LICENSE
beets_notify-0.2.1.dist-info/RECORD
