Metadata-Version: 2.4
Name: beets-notify
Version: 0.2.1
Summary: A beets plugin to send notifications when albums are imported
Project-URL: Repository, https://github.com/brege/beets-notify
Author-email: Wyatt Brege <wyatt@brege.org>
License-Expression: MIT
License-File: LICENSE
Requires-Dist: apprise>=1.0.0
Requires-Dist: pillow>=9.0.0
